ugbio_ppmseq/__init__.py
ugbio_ppmseq/ppmSeq_consts.py
ugbio_ppmseq/ppmSeq_qc_analysis.py
ugbio_ppmseq/ppmSeq_utils.py
ugbio_ppmseq/reports/ppmSeq_legacy_v5_illustration.png
ugbio_ppmseq/reports/ppmSeq_qc_report.ipynb
ugbio_ppmseq/reports/ppmSeq_v1_illustration.png
ugbio_ppmseq-1.20.0.dist-info/METADATA
ugbio_ppmseq-1.20.0.dist-info/WHEEL
ugbio_ppmseq-1.20.0.dist-info/entry_points.txt
ugbio_ppmseq-1.20.0.dist-info/top_level.txt
ugbio_ppmseq-1.20.0.dist-info/RECORD
