Metadata-Version: 2.4
Name: ugbio_ppmseq
Version: 1.20.0
Summary: Ultima Genomics ppmSeq utils
Author-email: Itai Rusinek <itai.rusinek@ultimagen.com>, Gat Krieger <gat.krieger@ultimagen.com>, Inbal Zelig <inbal.zelig@ultimagen.com>, Avigail Moldovan <avigail.moldovan@ultimagen.com>
License: Apache-2.0
Requires-Python: >=3.11
Requires-Dist: ugbio_core[parquet,reports,vcfbed]
